[
    {
        "id":0,
        "indexProduct":0,
        "img":"https://www.kroger.com/product/images/xlarge/front/0000000004011",
        "ProductName":"Banan",
        "type":"fruits",
        "Count":17,
        "MAinCount":1,
        "Price":700,
        "BasketCount":0 ,
        "BasketPrice":0,
        "InpNumberVal":0,
        "Seil":0,
        "AddingCount":1,
        "actual":false,
        "LearnMore":false,
        "x":false,
        "Actuallength":false,
        "DeletBasketCount":0,
        "DeletAddingCount":1,
        "Discription":"A banana is an elongated, edible fruit – botanically a berry[1][2] – produced by several kinds of large herbaceous flowering plants in the genus Musa.[3] In some countries"
  },
    {
        "id":1,
        "indexProduct":0,
        "img":"https://i.pinimg.com/originals/03/52/63/03526336ef23211c5a4c91db0ff12d17.png",
        "ProductName":"Apple",
        "type":"fruits",
        "Count":15,
        "MAinCount":1,
        "Price":750,
        "BasketCount":0,
        "BasketPrice":0,
        "InpNumberVal":0,
        "Seil":0,
        "AddingCount":1,
        "actual":false,
        "LearnMore":false,
        "x":false,
        "Actuallength":false,
        "DeletBasketCount":0,
        "DeletAddingCount":1,
        "Discription":"An apple is an edible fruit produced by an apple tree (Malus domestica). Apple trees are cultivated worldwide and are the most widely grown species in the genus Malus"
  },
    {
      "id":2,
      "indexProduct":0,
      "img":"https://pbs.twimg.com/media/ClxHKqxVAAEIazQ.jpg",
      "ProductName":"Orange",
      "type":"fruits",
      "Count":10,
      "MAinCount":1,
      "Price":600,
      "BasketCount":0,
      "BasketPrice":0,
      "InpNumberVal":0,
      "Seil":0,
      "AddingCount":1,
      "actual":false,
      "LearnMore":false,
      "x":false,
      "Actuallength":false,
      "DeletBasketCount":0,
      "DeletAddingCount":1,
      "Discription":"The orange is the fruit of various citrus species in the family Rutaceae (see list of plants known as orange); it primarily refers to Citrus × sinensis,[1] which is also called sweet orange"
  },
    {
      "id":3,
      "indexProduct":0,
      "img":"https://previews.123rf.com/images/photomaru/photomaru1610/photomaru161000008/65097111-isolated-pears-one-and-a-half-green-pear-fruit-isolated-on-white-background.jpg",
      "ProductName":"Pear",
      "type":"fruits",
      "Count":10,
      "MAinCount":1,
      "Price":600,
      "BasketCount":0,
      "BasketPrice":0,
      "InpNumberVal":0,
      "Seil":0,
      "AddingCount":1,
      "actual":false,
      "LearnMore":false,
      "x":false,
      "Actuallength":false,
      "DeletBasketCount":0,
      "DeletAddingCount":1,
      "Discription":"Pears are fruits produced and consumed around the world, growing on a tree and harvested in late Summer into October. The pear tree and shrub are a species of genus Pyrus "
},
  {
    "id":4,
    "indexProduct":0,
    "img":"https://chesenbio.com/wp-content/uploads/2019/11/1-MCP-on-apricot.png",
    "ProductName":"apricot",
    "type":"fruits",
    "Count":10,
    "MAinCount":1,
    "Price":600,
    "BasketCount":0,
    "BasketPrice":0,
    "InpNumberVal":0,
    "Seil":0,
    "AddingCount":1,
    "actual":false,
    "LearnMore":false,
    "x":false,
    "Actuallength":false,
    "DeletBasketCount":0,
    "DeletAddingCount":1,
    "Discription":"Apricot first appeared in English in the 16th century as abrecock from the Middle French, aubercot, or later from Portuguese, albricoque.[2] The specific name armeniaca was first "
},
{
  "id":5,
  "indexProduct":0,
  "img":"https://sb-assets.sgp1.cdn.digitaloceanspaces.com/product/main_image/36709/5d61cdf0-40cb-4c68-93bf-8194ab18016e.jpg",
  "ProductName":"grapes",
  "type":"fruits",
  "Count":10,
  "MAinCount":1,
  "Price":600,
  "BasketCount":0,
  "BasketPrice":0,
  "InpNumberVal":0,
  "Seil":0,
  "AddingCount":1,
  "actual":false,
  "LearnMore":false,
  "x":false,
  "Actuallength":false,
  "DeletBasketCount":0,
  "DeletAddingCount":1,
  "Discription":"Grapes are the fruit of a woody grape vine. Grapes can be eaten raw, or used for making wine, juice, and jelly/jam. Grapes come in different colours; red, purple, white"
},
{
"id":6,
"indexProduct":0,
"img":"https://www.lima-europe.eu/wp-content/uploads/2017/04/Cucumber.jpg",
"ProductName":"Cucumber",
"type":"vegetables",
"Count":15,
"MAinCount":1,
"Price":800,
"BasketCount":0,
"BasketPrice":0,
"InpNumberVal":0,
"Seil":0,
"AddingCount":1,
"actual":false,
"LearnMore":false,
"x":false,
"Actuallength":false,
"DeletBasketCount":0,
"DeletAddingCount":1,
"Discription":"Cucumber is a software tool that supports behavior-driven development (BDD).[7][8][9][10] Central to the Cucumber BDD approach is its ordinary language parser called Gherkin"
},
{
"id":7,
"indexProduct":0,
"img":"https://media.istockphoto.com/photos/tomato-isolated-on-white-background-picture-id466175630?k=6&m=466175630&s=612x612&w=0&h=fu_mQBjGJZIliOWwCR0Vf2myRvKWyQDsymxEIi8tZ38=",
"ProductName":"Tomato",
"type":"vegetables",
"Count":9,
"MAinCount":1,
"Price":1400,
"BasketCount":0,
"BasketPrice":0,
"InpNumberVal":0,
"Seil":0,
"AddingCount":1,
"actual":false,
"LearnMore":false,
"x":false,
"Actuallength":false,
"DeletBasketCount":0,
"DeletAddingCount":1,
"Discription":"The tomato is the edible berry of the plant Solanum lycopersicum,[1][2] commonly known as a tomato plant. The species originated in western South America and Central America"
}
]